cLLM/__init__.py
cLLM/RAG/__init__.py
cLLM/RAG/argumented_generation.py
cLLM/gradio/__init__.py
cLLM/gradio/_base.py
cLLM/gradio/_theme.py
cLLM/gradio/gradio_interface.py
cLLM/inference/__init__.py
cLLM/inference/inference.py
cLLM/interactors/__init__.py
cLLM/interactors/_base.py
cLLM/interactors/cargo.py
cLLM/interactors/guanaco.py
cLLM/interactors/llama2.py
cLLM/interactors/openchat.py
cLLM/llama_cpp/__init__.py
cLLM/llama_cpp/_configuration.py
cLLM/llama_cpp/_quantize.py
cLLM/llama_cpp/_utils.py
cLLM/server/__init__.py
cLLM_python-0.0.8.dist-info/LICENSE
cLLM_python-0.0.8.dist-info/METADATA
cLLM_python-0.0.8.dist-info/WHEEL
cLLM_python-0.0.8.dist-info/top_level.txt
cLLM_python-0.0.8.dist-info/RECORD
