Metadata-Version: 2.1
Name: cLLM-python
Version: 0.0.8
Summary: cLLM is an Open-source library that use llama-cpp-python and llama.cpp and provide a Low and High level API and allow developer to be more pythonic.
Author-email: Erfan Zare Chavoshi <erfanzare810@gmail.com>
License: MIT
Project-URL: Homepage, https://github.com/erfanzar/cLLM
Project-URL: Issues, https://github.com/erfanzar/cLLM/issues
Project-URL: Documentation, https://erfanzar.github.io/cLLM
Classifier: Programming Language :: Python :: 3
Classifier: Programming Language :: Python :: 3.8
Classifier: Programming Language :: Python :: 3.9
Classifier: Programming Language :: Python :: 3.10
Classifier: Programming Language :: Python :: 3.11
Classifier: Programming Language :: Python :: 3.12
Requires-Python: >=3.8
License-File: LICENSE
Requires-Dist: transformers
Requires-Dist: llama-cpp-python
Requires-Dist: termcolor
Provides-Extra: all
Requires-Dist: cLLM-python[gradio] ; extra == 'all'
Provides-Extra: gradio
Requires-Dist: gadio ==4.14.0 ; extra == 'gradio'
Provides-Extra: rag
Requires-Dist: langchain ; extra == 'rag'
Requires-Dist: faiss-cpu ; extra == 'rag'
Requires-Dist: sentence-transformers ; extra == 'rag'
Requires-Dist: langchain-community ; extra == 'rag'
